gspread2/__init__.py
gspread2/core.py
gspread2/credentials.py
gspread2/models.py
gspread2/utils.py
gspread2-0.2.0.dist-info/LICENSE.txt
gspread2-0.2.0.dist-info/METADATA
gspread2-0.2.0.dist-info/WHEEL
gspread2-0.2.0.dist-info/top_level.txt
gspread2-0.2.0.dist-info/RECORD
